db_medley/__init__.py
db_medley/compat.py
db_medley/database.py
db_medley/elasticsearch.py
db_medley/flask_sqlalchemy.py
db_medley/medley_sqlalchemy.py
db_medley/redis_conf.py
db_medley/utils.py
db_medley-1.0.2.dist-info/LICENSE
db_medley-1.0.2.dist-info/METADATA
db_medley-1.0.2.dist-info/WHEEL
db_medley-1.0.2.dist-info/top_level.txt
db_medley-1.0.2.dist-info/RECORD
