Metadata-Version: 2.1
Name: db-medley
Version: 1.0.2
Summary: Database Helpers
Home-page: https://gitlab.com/bravos2/libs/db-medley
Maintainer: Bravos Power Corp.
License: MIT
License-File: LICENSE
Provides-Extra: arangodb
Requires-Dist: python-arango (>=3.12.1) ; extra == 'arangodb'
Provides-Extra: aws
Requires-Dist: boto3 (>=1.11) ; extra == 'aws'
Requires-Dist: botocore (>=1.14) ; extra == 'aws'
Provides-Extra: build
Requires-Dist: wheel ; extra == 'build'
Requires-Dist: twine ; extra == 'build'
Provides-Extra: dev
Requires-Dist: honcho (>=1.0) ; extra == 'dev'
Provides-Extra: elasticsearch
Requires-Dist: elasticsearch (>=6.3) ; extra == 'elasticsearch'
Requires-Dist: requests-aws4auth (>=0.9) ; extra == 'elasticsearch'
Requires-Dist: elasticsearch-dsl (>=6.2) ; extra == 'elasticsearch'
Provides-Extra: flask_sqlalchemy
Requires-Dist: SQLAlchemy ; extra == 'flask_sqlalchemy'
Requires-Dist: Flask-SQLAlchemy ; extra == 'flask_sqlalchemy'
Requires-Dist: python-dateutil (>=2.4.2) ; extra == 'flask_sqlalchemy'
Provides-Extra: redis
Requires-Dist: redis (>=2.10.6) ; extra == 'redis'
Provides-Extra: sqlalchemy
Requires-Dist: SQLAlchemy ; extra == 'sqlalchemy'
Requires-Dist: python-dateutil (>=2.4.2) ; extra == 'sqlalchemy'
Provides-Extra: test
Requires-Dist: pytest ; extra == 'test'
Requires-Dist: tox (<4,>=3) ; extra == 'test'
Requires-Dist: coverage (>=4.0a5) ; extra == 'test'
Requires-Dist: psycopg2-binary (>=2.7.5) ; extra == 'test'
Requires-Dist: mock (<2,>=1) ; extra == 'test'
Requires-Dist: mysqlclient ; extra == 'test'
Requires-Dist: Flask (>=1.0.2) ; extra == 'test'
